cellphonedb/__init__.py
cellphonedb/cellphonedb_cli.py
cellphonedb/src/__init__.py
cellphonedb/src/api_endpoints/__init__.py
cellphonedb/src/api_endpoints/terminal_api/__init__.py
cellphonedb/src/api_endpoints/terminal_api/method_terminal_api_endpoints/__init__.py
cellphonedb/src/api_endpoints/terminal_api/method_terminal_api_endpoints/method_terminal_commands.py
cellphonedb/src/api_endpoints/web_api/__init__.py
cellphonedb/src/api_endpoints/web_api/routes.py
cellphonedb/src/api_endpoints/web_api/web_api_endpoint_base.py
cellphonedb/src/api_endpoints/web_api/query_web_api_endpoints/__init__.py
cellphonedb/src/api_endpoints/web_api/query_web_api_endpoints/query_web_api_routes.py
cellphonedb/src/api_endpoints/web_api/query_web_api_endpoints/web_endpoint_query_autocomplete.py
cellphonedb/src/api_endpoints/web_api/query_web_api_endpoints/web_endpoint_query_find_interactions_by_element.py
cellphonedb/src/api_endpoints/web_api/query_web_api_endpoints/complex/__init__.py
cellphonedb/src/api_endpoints/web_api/query_web_api_endpoints/complex/query_complex_web_api_routes.py
cellphonedb/src/api_endpoints/web_api/query_web_api_endpoints/complex/web_endpoint_query_complex_deconvoluted.py
cellphonedb/src/api_endpoints/web_api/query_web_api_endpoints/interaction/__init__.py
cellphonedb/src/api_endpoints/web_api/query_web_api_endpoints/interaction/query_interaction_web_api_routes.py
cellphonedb/src/api_endpoints/web_api/query_web_api_endpoints/interaction/web_endpoint_query_interaction_gene.py
cellphonedb/src/app/__init__.py
cellphonedb/src/app/app_config.py
cellphonedb/src/app/app_logger.py
cellphonedb/src/app/cellphonedb_app.py
cellphonedb/src/app/cpdb_app.py
cellphonedb/src/app/config/base_config.yml
cellphonedb/src/app/config/core.yml
cellphonedb/src/app/config/docker_test.yml
cellphonedb/src/app/config/postgres_local.yml
cellphonedb/src/app/config/test.yml
cellphonedb/src/app/flask/__init__.py
cellphonedb/src/app/flask/flask_app.py
CellPhoneDBu-1.1.1.7.dist-info/METADATA
CellPhoneDBu-1.1.1.7.dist-info/WHEEL
CellPhoneDBu-1.1.1.7.dist-info/entry_points.txt
CellPhoneDBu-1.1.1.7.dist-info/top_level.txt
CellPhoneDBu-1.1.1.7.dist-info/RECORD
